{
  "meta": {
    "updatedAt": "2026-05-31T07:54:04.113Z",
    "source": "the-odds-api",
    "sport": "auto",
    "regions": "eu",
    "market": "h2h",
    "matches": 28,
    "valuePicks": 0,
    "books": 22
  },
  "TEAMS": {
    "bragan": {
      "id": "bragan",
      "name": "Bragantino-SP",
      "code": "BRA",
      "color": "#5a6b8c",
      "conf": "—",
      "fifa": 55,
      "form": "",
      "known": false
    },
    "intbr": {
      "id": "intbr",
      "name": "Internacional",
      "code": "INT-BR",
      "color": "#e5484d",
      "conf": "Club",
      "elo": 1805,
      "form": "WDWWL",
      "known": true
    },
    "vasco": {
      "id": "vasco",
      "name": "Vasco da Gama",
      "code": "VAS",
      "color": "#1a1a1a",
      "conf": "Club",
      "elo": 1745,
      "form": "LWDLW",
      "known": true
    },
    "atmg": {
      "id": "atmg",
      "name": "Atlético Mineiro",
      "code": "CAM",
      "color": "#1a1a1a",
      "conf": "Club",
      "elo": 1820,
      "form": "WWLWD",
      "known": true
    },
    "pal": {
      "id": "pal",
      "name": "Palmeiras",
      "code": "PAL",
      "color": "#0aa05a",
      "conf": "Club",
      "elo": 1870,
      "form": "WWDWW",
      "known": true
    },
    "chapec": {
      "id": "chapec",
      "name": "Chapecoense",
      "code": "CHA",
      "color": "#5a6b8c",
      "conf": "—",
      "fifa": 55,
      "form": "",
      "known": false
    },
    "cru": {
      "id": "cru",
      "name": "Cruzeiro",
      "code": "CRU",
      "color": "#1f5fd6",
      "conf": "Club",
      "elo": 1795,
      "form": "WDWLW",
      "known": true
    },
    "fluf": {
      "id": "fluf",
      "name": "Fluminense",
      "code": "FLU",
      "color": "#0a7d3c",
      "conf": "Club",
      "elo": 1790,
      "form": "DWLWD",
      "known": true
    },
    "remo": {
      "id": "remo",
      "name": "Remo",
      "code": "REM",
      "color": "#5a6b8c",
      "conf": "—",
      "fifa": 55,
      "form": "",
      "known": false
    },
    "spa": {
      "id": "spa",
      "name": "São Paulo",
      "code": "SAO",
      "color": "#e5484d",
      "conf": "Club",
      "elo": 1810,
      "form": "WWDLW",
      "known": true
    },
    "almeri": {
      "id": "almeri",
      "name": "Almería",
      "code": "ALM",
      "color": "#5a6b8c",
      "conf": "—",
      "fifa": 55,
      "form": "",
      "known": false
    },
    "realva": {
      "id": "realva",
      "name": "Real Valladolid CF",
      "code": "REA",
      "color": "#5a6b8c",
      "conf": "—",
      "fifa": 55,
      "form": "",
      "known": false
    },
    "burgos": {
      "id": "burgos",
      "name": "Burgos CF",
      "code": "BUR",
      "color": "#5a6b8c",
      "conf": "—",
      "fifa": 55,
      "form": "",
      "known": false
    },
    "andorr": {
      "id": "andorr",
      "name": "Andorra CF",
      "code": "AND",
      "color": "#5a6b8c",
      "conf": "—",
      "fifa": 55,
      "form": "",
      "known": false
    },
    "cdcast": {
      "id": "cdcast",
      "name": "CD Castellón",
      "code": "CDC",
      "color": "#5a6b8c",
      "conf": "—",
      "fifa": 55,
      "form": "",
      "known": false
    },
    "sdeiba": {
      "id": "sdeiba",
      "name": "SD Eibar",
      "code": "SDE",
      "color": "#5a6b8c",
      "conf": "—",
      "fifa": 55,
      "form": "",
      "known": false
    },
    "realra": {
      "id": "realra",
      "name": "Real Racing Club de Santander",
      "code": "REA",
      "color": "#5a6b8c",
      "conf": "—",
      "fifa": 55,
      "form": "",
      "known": false
    },
    "cadizc": {
      "id": "cadizc",
      "name": "Cádiz CF",
      "code": "CDI",
      "color": "#5a6b8c",
      "conf": "—",
      "fifa": 55,
      "form": "",
      "known": false
    },
    "deport": {
      "id": "deport",
      "name": "Deportes Limache",
      "code": "DEP",
      "color": "#5a6b8c",
      "conf": "—",
      "fifa": 55,
      "form": "",
      "known": false
    },
    "laspal": {
      "id": "laspal",
      "name": "Las Palmas",
      "code": "LAS",
      "color": "#5a6b8c",
      "conf": "—",
      "fifa": 55,
      "form": "",
      "known": false
    },
    "zarago": {
      "id": "zarago",
      "name": "Zaragoza",
      "code": "ZAR",
      "color": "#5a6b8c",
      "conf": "—",
      "fifa": 55,
      "form": "",
      "known": false
    },
    "malaga": {
      "id": "malaga",
      "name": "Málaga",
      "code": "MLA",
      "color": "#5a6b8c",
      "conf": "—",
      "fifa": 55,
      "form": "",
      "known": false
    },
    "legane": {
      "id": "legane",
      "name": "Leganés",
      "code": "LEG",
      "color": "#5a6b8c",
      "conf": "—",
      "fifa": 55,
      "form": "",
      "known": false
    },
    "cdmira": {
      "id": "cdmira",
      "name": "CD Mirandés",
      "code": "CDM",
      "color": "#5a6b8c",
      "conf": "—",
      "fifa": 55,
      "form": "",
      "known": false
    },
    "cordob": {
      "id": "cordob",
      "name": "Córdoba",
      "code": "CRD",
      "color": "#5a6b8c",
      "conf": "—",
      "fifa": 55,
      "form": "",
      "known": false
    },
    "sdhues": {
      "id": "sdhues",
      "name": "SD Huesca",
      "code": "SDH",
      "color": "#5a6b8c",
      "conf": "—",
      "fifa": 55,
      "form": "",
      "known": false
    },
    "saober": {
      "id": "saober",
      "name": "São Bernardo",
      "code": "SOB",
      "color": "#5a6b8c",
      "conf": "—",
      "fifa": 55,
      "form": "",
      "known": false
    },
    "gremio": {
      "id": "gremio",
      "name": "Grêmio Novorizontino",
      "code": "GRM",
      "color": "#5a6b8c",
      "conf": "—",
      "fifa": 55,
      "form": "",
      "known": false
    },
    "londri": {
      "id": "londri",
      "name": "Londrina",
      "code": "LON",
      "color": "#5a6b8c",
      "conf": "—",
      "fifa": 55,
      "form": "",
      "known": false
    },
    "vilano": {
      "id": "vilano",
      "name": "Vila Nova",
      "code": "VIL",
      "color": "#5a6b8c",
      "conf": "—",
      "fifa": 55,
      "form": "",
      "known": false
    },
    "ceara": {
      "id": "ceara",
      "name": "Ceará",
      "code": "CEA",
      "color": "#5a6b8c",
      "conf": "—",
      "fifa": 55,
      "form": "",
      "known": false
    },
    "operar": {
      "id": "operar",
      "name": "Operario PR",
      "code": "OPE",
      "color": "#5a6b8c",
      "conf": "—",
      "fifa": 55,
      "form": "",
      "known": false
    },
    "cuiaba": {
      "id": "cuiaba",
      "name": "Cuiabá",
      "code": "CUI",
      "color": "#5a6b8c",
      "conf": "—",
      "fifa": 55,
      "form": "",
      "known": false
    },
    "clubed": {
      "id": "clubed",
      "name": "Clube de Regatas Brasil",
      "code": "CLU",
      "color": "#5a6b8c",
      "conf": "—",
      "fifa": 55,
      "form": "",
      "known": false
    },
    "pontep": {
      "id": "pontep",
      "name": "Ponte Preta",
      "code": "PON",
      "color": "#5a6b8c",
      "conf": "—",
      "fifa": 55,
      "form": "",
      "known": false
    },
    "bot": {
      "id": "bot",
      "name": "Botafogo",
      "code": "BOT",
      "color": "#1a1a1a",
      "conf": "Club",
      "elo": 1840,
      "form": "WDWWL",
      "known": true
    },
    "gent": {
      "id": "gent",
      "name": "Gent",
      "code": "GEN",
      "color": "#5a6b8c",
      "conf": "—",
      "fifa": 55,
      "form": "",
      "known": false
    },
    "genk": {
      "id": "genk",
      "name": "Genk",
      "code": "GEN",
      "color": "#5a6b8c",
      "conf": "—",
      "fifa": 55,
      "form": "",
      "known": false
    },
    "bkhack": {
      "id": "bkhack",
      "name": "BK Hacken",
      "code": "BKH",
      "color": "#5a6b8c",
      "conf": "—",
      "fifa": 55,
      "form": "",
      "known": false
    },
    "hammar": {
      "id": "hammar",
      "name": "Hammarby IF",
      "code": "HAM",
      "color": "#5a6b8c",
      "conf": "—",
      "fifa": 55,
      "form": "",
      "known": false
    },
    "degerf": {
      "id": "degerf",
      "name": "Degerfors IF",
      "code": "DEG",
      "color": "#5a6b8c",
      "conf": "—",
      "fifa": 55,
      "form": "",
      "known": false
    },
    "ifbrom": {
      "id": "ifbrom",
      "name": "IF Brommapojkarna",
      "code": "IFB",
      "color": "#5a6b8c",
      "conf": "—",
      "fifa": 55,
      "form": "",
      "known": false
    },
    "vaster": {
      "id": "vaster",
      "name": "Västerås SK",
      "code": "VST",
      "color": "#5a6b8c",
      "conf": "—",
      "fifa": 55,
      "form": "",
      "known": false
    },
    "ifkgot": {
      "id": "ifkgot",
      "name": "IFK Goteborg",
      "code": "IFK",
      "color": "#5a6b8c",
      "conf": "—",
      "fifa": 55,
      "form": "",
      "known": false
    },
    "coquim": {
      "id": "coquim",
      "name": "Coquimbo Unido",
      "code": "COQ",
      "color": "#5a6b8c",
      "conf": "—",
      "fifa": 55,
      "form": "",
      "known": false
    },
    "huachi": {
      "id": "huachi",
      "name": "Huachipato",
      "code": "HUA",
      "color": "#5a6b8c",
      "conf": "—",
      "fifa": 55,
      "form": "",
      "known": false
    },
    "univer": {
      "id": "univer",
      "name": "Universidad Católica (CHI)",
      "code": "UNI",
      "color": "#5a6b8c",
      "conf": "—",
      "fifa": 55,
      "form": "",
      "known": false
    },
    "ohiggi": {
      "id": "ohiggi",
      "name": "O'Higgins",
      "code": "OHI",
      "color": "#5a6b8c",
      "conf": "—",
      "fifa": 55,
      "form": "",
      "known": false
    },
    "everto": {
      "id": "everto",
      "name": "Everton de Viña del Mar",
      "code": "EVE",
      "color": "#5a6b8c",
      "conf": "—",
      "fifa": 55,
      "form": "",
      "known": false
    },
    "palest": {
      "id": "palest",
      "name": "Palestino",
      "code": "PAL",
      "color": "#5a6b8c",
      "conf": "—",
      "fifa": 55,
      "form": "",
      "known": false
    },
    "audaxi": {
      "id": "audaxi",
      "name": "Audax Italiano",
      "code": "AUD",
      "color": "#5a6b8c",
      "conf": "—",
      "fifa": 55,
      "form": "",
      "known": false
    },
    "tianji": {
      "id": "tianji",
      "name": "Tianjin Jinmen Tiger FC",
      "code": "TIA",
      "color": "#5a6b8c",
      "conf": "—",
      "fifa": 55,
      "form": "",
      "known": false
    },
    "dalian": {
      "id": "dalian",
      "name": "Dalian Yingbo",
      "code": "DAL",
      "color": "#5a6b8c",
      "conf": "—",
      "fifa": 55,
      "form": "",
      "known": false
    },
    "wuhant": {
      "id": "wuhant",
      "name": "Wuhan Three Towns",
      "code": "WUH",
      "color": "#5a6b8c",
      "conf": "—",
      "fifa": 55,
      "form": "",
      "known": false
    },
    "yunnan": {
      "id": "yunnan",
      "name": "Yunnan Yukun",
      "code": "YUN",
      "color": "#5a6b8c",
      "conf": "—",
      "fifa": 55,
      "form": "",
      "known": false
    }
  },
  "BOOKS": {
    "betsson": {
      "name": "Betsson",
      "abbr": "BETS",
      "color": "#ff8a1e",
      "url": "#"
    },
    "unibet": {
      "name": "Unibet",
      "abbr": "UNIB",
      "color": "#0aa05a",
      "url": "#"
    },
    "winamax": {
      "name": "Winamax",
      "abbr": "WINA",
      "color": "#e5484d",
      "url": "#"
    },
    "onexbet": {
      "name": "1xBet",
      "abbr": "1XBE",
      "color": "#1f5fd6",
      "url": "#"
    },
    "nordicbet": {
      "name": "Nordic Bet",
      "abbr": "NORD",
      "color": "#1f3a93",
      "url": "#"
    },
    "sport888": {
      "name": "888sport",
      "abbr": "888S",
      "color": "#ff8a1e",
      "url": "#"
    },
    "williamhill": {
      "name": "William Hill",
      "abbr": "WILL",
      "color": "#1f5fd6",
      "url": "#"
    },
    "marathonbet": {
      "name": "Marathon Bet",
      "abbr": "MARA",
      "color": "#1f5fd6",
      "url": "#"
    },
    "coolbet": {
      "name": "Coolbet",
      "abbr": "COOL",
      "color": "#0aa05a",
      "url": "#"
    },
    "leovegas": {
      "name": "LeoVegas",
      "abbr": "LEOV",
      "color": "#e5a000",
      "url": "#"
    },
    "pmu": {
      "name": "PMU",
      "abbr": "PMU",
      "color": "#5a6b8c",
      "url": "#"
    },
    "betclic": {
      "name": "Betclic",
      "abbr": "BETC",
      "color": "#e5484d",
      "url": "#"
    },
    "pinnacle": {
      "name": "Pinnacle",
      "abbr": "PINN",
      "color": "#3a4660",
      "url": "#"
    },
    "gtbets": {
      "name": "GTbets",
      "abbr": "GTBE",
      "color": "#5a6b8c",
      "url": "#"
    },
    "matchbook": {
      "name": "Matchbook",
      "abbr": "MATC",
      "color": "#5a6b8c",
      "url": "#"
    },
    "everygame": {
      "name": "Everygame",
      "abbr": "EVER",
      "color": "#5a6b8c",
      "url": "#"
    },
    "tipico": {
      "name": "Tipico",
      "abbr": "TIPI",
      "color": "#c8102e",
      "url": "#"
    },
    "betonlineag": {
      "name": "BetOnline.ag",
      "abbr": "BETO",
      "color": "#1a1a1a",
      "url": "#"
    },
    "codere": {
      "name": "Codere",
      "abbr": "CODE",
      "color": "#0aa05a",
      "url": "#"
    },
    "betfair": {
      "name": "Betfair",
      "abbr": "BETF",
      "color": "#ffb01f",
      "url": "#"
    },
    "betanysports": {
      "name": "BetAnything",
      "abbr": "BETA",
      "color": "#5a6b8c",
      "url": "#"
    },
    "suprabets": {
      "name": "Suprabets",
      "abbr": "SUPR",
      "color": "#5a6b8c",
      "url": "#"
    }
  },
  "MATCHES": [
    {
      "id": "c7a8f2d76c79a48a99a5b8d5486ac1ba",
      "group": "dom, 31 may",
      "time": "16:00",
      "home": "bragan",
      "away": "intbr",
      "odds": {
        "home": {
          "betsson": 2.12,
          "unibet": 2.16,
          "winamax": 2.05,
          "onexbet": 2.18,
          "nordicbet": 2.12,
          "sport888": 2.1,
          "williamhill": 2.1,
          "marathonbet": 2.12,
          "coolbet": 2.12,
          "leovegas": 2.12,
          "pmu": 2.08,
          "betclic": 2.05,
          "pinnacle": 2.2,
          "gtbets": 2.11,
          "matchbook": 2.24,
          "everygame": 2.15,
          "tipico": 2.1,
          "betonlineag": 2.1,
          "codere": 2.13,
          "betfair": 2.24,
          "betanysports": 2.1
        },
        "draw": {
          "betsson": 3.25,
          "unibet": 3.3,
          "winamax": 3.35,
          "onexbet": 3.38,
          "nordicbet": 3.25,
          "sport888": 3.1,
          "williamhill": 3.1,
          "marathonbet": 3.28,
          "coolbet": 3.38,
          "leovegas": 3.25,
          "pmu": 3.2,
          "betclic": 3.35,
          "pinnacle": 3.4,
          "gtbets": 3.27,
          "matchbook": 3.5,
          "everygame": 3.3,
          "tipico": 3.2,
          "betonlineag": 3.37,
          "codere": 3.35,
          "betfair": 3.5,
          "betanysports": 3.37
        },
        "away": {
          "betsson": 3.35,
          "unibet": 3.35,
          "winamax": 3.2,
          "onexbet": 3.48,
          "nordicbet": 3.35,
          "sport888": 3.3,
          "williamhill": 3.3,
          "marathonbet": 3.38,
          "coolbet": 3.55,
          "leovegas": 3.3,
          "pmu": 3.25,
          "betclic": 3.4,
          "pinnacle": 3.5,
          "gtbets": 3.37,
          "matchbook": 3.7,
          "everygame": 3.35,
          "tipico": 3.4,
          "betonlineag": 3.61,
          "codere": 3.4,
          "betfair": 3.7,
          "betanysports": 3.61
        }
      },
      "model": {
        "home": 0.44122638089938426,
        "draw": 0.2840492629857417,
        "away": 0.27472435611487395,
        "fromMarket": true
      }
    },
    {
      "id": "02b486785d30a937dbc754ae9d14a1ec",
      "group": "dom, 31 may",
      "time": "21:00",
      "home": "vasco",
      "away": "atmg",
      "odds": {
        "home": {
          "winamax": 1.9,
          "onexbet": 1.96,
          "unibet": 1.94,
          "sport888": 1.91,
          "williamhill": 1.91,
          "marathonbet": 1.91,
          "betsson": 1.92,
          "nordicbet": 1.92,
          "coolbet": 1.99,
          "pmu": 1.88,
          "leovegas": 1.92,
          "betclic": 1.89,
          "pinnacle": 1.95,
          "gtbets": 1.98,
          "everygame": 1.91,
          "tipico": 1.85,
          "betonlineag": 1.94,
          "matchbook": 2,
          "codere": 1.96,
          "betfair": 1.99,
          "betanysports": 1.95
        },
        "draw": {
          "winamax": 3.4,
          "onexbet": 3.5,
          "unibet": 3.35,
          "sport888": 3.25,
          "williamhill": 3.25,
          "marathonbet": 3.4,
          "betsson": 3.45,
          "nordicbet": 3.45,
          "coolbet": 3.43,
          "pmu": 3.25,
          "leovegas": 3.3,
          "betclic": 3.43,
          "pinnacle": 3.53,
          "gtbets": 3.46,
          "everygame": 3.4,
          "tipico": 3.4,
          "betonlineag": 3.45,
          "matchbook": 3.65,
          "codere": 3.45,
          "betfair": 3.65,
          "betanysports": 3.5
        },
        "away": {
          "winamax": 3.65,
          "onexbet": 4.05,
          "unibet": 3.95,
          "sport888": 3.8,
          "williamhill": 3.8,
          "marathonbet": 3.94,
          "betsson": 3.7,
          "nordicbet": 3.7,
          "coolbet": 3.9,
          "pmu": 3.85,
          "leovegas": 3.9,
          "betclic": 3.85,
          "pinnacle": 4.19,
          "gtbets": 3.82,
          "everygame": 3.9,
          "tipico": 4,
          "betonlineag": 4.08,
          "matchbook": 4.3,
          "codere": 3.85,
          "betfair": 4.3,
          "betanysports": 3.95
        }
      },
      "model": {
        "home": 0.23039592577267437,
        "draw": 0.2571176879944755,
        "away": 0.5124863862328501,
        "lambdaH": 1.0817820512820515,
        "lambdaA": 1.713448717948718,
        "ratingH": 1742.2,
        "ratingA": 1834,
        "sup": -0.6316666666666663
      }
    },
    {
      "id": "90e012b4ee7a33eff3dfca2e9008eb89",
      "group": "dom, 31 may",
      "time": "21:00",
      "home": "pal",
      "away": "chapec",
      "odds": {
        "home": {
          "winamax": 1.29,
          "nordicbet": 1.29,
          "onexbet": 1.31,
          "unibet": 1.27,
          "betsson": 1.29,
          "marathonbet": 1.28,
          "sport888": 1.29,
          "williamhill": 1.29,
          "coolbet": 1.31,
          "pmu": 1.21,
          "leovegas": 1.23,
          "betclic": 1.29,
          "pinnacle": 1.31,
          "gtbets": 1.29,
          "matchbook": 1.33,
          "everygame": 1.25,
          "tipico": 1.25,
          "betonlineag": 1.29,
          "codere": 1.32,
          "betfair": 1.33,
          "betanysports": 1.29
        },
        "draw": {
          "winamax": 5.3,
          "nordicbet": 5.4,
          "onexbet": 5.68,
          "unibet": 5.75,
          "betsson": 5.4,
          "marathonbet": 5.4,
          "sport888": 5,
          "williamhill": 5,
          "coolbet": 5.35,
          "pmu": 5.5,
          "leovegas": 5.6,
          "betclic": 5.25,
          "pinnacle": 5.86,
          "gtbets": 5.52,
          "matchbook": 6,
          "everygame": 5.5,
          "tipico": 5.5,
          "betonlineag": 5.65,
          "codere": 5.4,
          "betfair": 6,
          "betanysports": 5.65
        },
        "away": {
          "winamax": 7.5,
          "nordicbet": 9.8,
          "onexbet": 9.85,
          "unibet": 11.5,
          "betsson": 9.8,
          "marathonbet": 9.4,
          "sport888": 9,
          "williamhill": 9,
          "coolbet": 10,
          "pmu": 11,
          "leovegas": 11,
          "betclic": 8.5,
          "pinnacle": 10.01,
          "gtbets": 9.78,
          "matchbook": 11.5,
          "everygame": 9.5,
          "tipico": 9.5,
          "betonlineag": 10.5,
          "codere": 8.6,
          "betfair": 11.5,
          "betanysports": 10.5
        }
      },
      "model": {
        "home": 0.7324527766823118,
        "draw": 0.17127045833666374,
        "away": 0.0962767649810245,
        "fromMarket": true
      }
    },
    {
      "id": "46e7f1fb8b675fd32159227996af35d8",
      "group": "lun, 01 jun",
      "time": "01:30",
      "home": "cru",
      "away": "fluf",
      "odds": {
        "home": {
          "onexbet": 2.03,
          "winamax": 1.96,
          "nordicbet": 1.98,
          "unibet": 2.05,
          "williamhill": 1.95,
          "betsson": 1.98,
          "sport888": 1.95,
          "marathonbet": 1.97,
          "pmu": 1.97,
          "leovegas": 2.02,
          "coolbet": 2.02,
          "betclic": 1.94,
          "pinnacle": 2,
          "gtbets": 2.09,
          "everygame": 1.95,
          "tipico": 1.95,
          "betonlineag": 2.02,
          "codere": 2.03,
          "betfair": 2.08,
          "betanysports": 2.02,
          "matchbook": 2.08
        },
        "draw": {
          "onexbet": 3.42,
          "winamax": 3.35,
          "nordicbet": 3.35,
          "unibet": 3.4,
          "williamhill": 3.2,
          "betsson": 3.35,
          "sport888": 3.2,
          "marathonbet": 3.32,
          "pmu": 3.3,
          "leovegas": 3.35,
          "coolbet": 3.35,
          "betclic": 3.22,
          "pinnacle": 3.46,
          "gtbets": 3.29,
          "everygame": 3.3,
          "tipico": 3.3,
          "betonlineag": 3.38,
          "codere": 3.35,
          "betfair": 3.45,
          "betanysports": 3.38,
          "matchbook": 3.45
        },
        "away": {
          "onexbet": 3.91,
          "winamax": 3.45,
          "nordicbet": 3.7,
          "unibet": 3.55,
          "williamhill": 3.7,
          "betsson": 3.7,
          "sport888": 3.7,
          "marathonbet": 3.8,
          "pmu": 3.45,
          "leovegas": 3.5,
          "coolbet": 3.9,
          "betclic": 3.53,
          "pinnacle": 3.99,
          "gtbets": 3.77,
          "everygame": 3.85,
          "tipico": 3.7,
          "betonlineag": 3.86,
          "codere": 3.7,
          "betfair": 4.1,
          "betanysports": 3.86,
          "matchbook": 4.2
        }
      },
      "model": {
        "home": 0.42565146294654427,
        "draw": 0.27051119441569144,
        "away": 0.30383734263776435,
        "lambdaH": 1.5219358974358976,
        "lambdaA": 1.253602564102564,
        "ratingH": 1809,
        "ratingA": 1792.8,
        "sup": 0.2683333333333337
      }
    },
    {
      "id": "9738488af51ff6e91ae3bc270a0f18b7",
      "group": "lun, 01 jun",
      "time": "01:30",
      "home": "remo",
      "away": "spa",
      "odds": {
        "home": {
          "pmu": 2.85,
          "unibet": 2.9,
          "winamax": 2.65,
          "leovegas": 2.88,
          "coolbet": 2.9,
          "sport888": 2.8,
          "williamhill": 2.8,
          "onexbet": 2.88,
          "gtbets": 2.84,
          "pinnacle": 2.87,
          "tipico": 2.8,
          "marathonbet": 2.8,
          "betonlineag": 2.86,
          "everygame": 2.75,
          "betanysports": 2.86,
          "codere": 2.85,
          "nordicbet": 2.78,
          "betsson": 2.78,
          "betfair": 3,
          "matchbook": 3
        },
        "draw": {
          "pmu": 3.1,
          "unibet": 3.2,
          "winamax": 3.15,
          "leovegas": 3.15,
          "coolbet": 3.15,
          "sport888": 3,
          "williamhill": 3,
          "onexbet": 3.27,
          "gtbets": 3.18,
          "pinnacle": 3.27,
          "tipico": 3.1,
          "marathonbet": 3.18,
          "betonlineag": 3.25,
          "everygame": 3.1,
          "betanysports": 3.25,
          "codere": 3.25,
          "nordicbet": 3.15,
          "betsson": 3.15,
          "betfair": 3.35,
          "matchbook": 3.35
        },
        "away": {
          "pmu": 2.38,
          "unibet": 2.45,
          "winamax": 2.35,
          "leovegas": 2.4,
          "coolbet": 2.58,
          "sport888": 2.45,
          "williamhill": 2.45,
          "onexbet": 2.57,
          "gtbets": 2.43,
          "pinnacle": 2.61,
          "tipico": 2.45,
          "marathonbet": 2.5,
          "betonlineag": 2.55,
          "everygame": 2.55,
          "betanysports": 2.55,
          "codere": 2.5,
          "nordicbet": 2.52,
          "betsson": 2.52,
          "betfair": 2.64,
          "matchbook": 2.68
        }
      },
      "model": {
        "home": 0.3301981555223953,
        "draw": 0.29519155339324354,
        "away": 0.37461029108436117,
        "fromMarket": true
      }
    },
    {
      "id": "906247c494cc4d838337689527fbb550",
      "group": "dom, 31 may",
      "time": "18:30",
      "home": "almeri",
      "away": "realva",
      "odds": {
        "home": {
          "leovegas": 1.33,
          "unibet": 1.36,
          "nordicbet": 1.39,
          "pmu": 1.28,
          "betsson": 1.39,
          "codere": 1.38,
          "onexbet": 1.39,
          "pinnacle": 1.4,
          "marathonbet": 1.35,
          "williamhill": 1.36,
          "betclic": 1.38,
          "winamax": 1.37,
          "tipico": 1.35,
          "betfair": 1.42,
          "betonlineag": 1.36,
          "coolbet": 1.42,
          "betanysports": 1.35,
          "matchbook": 1.42
        },
        "draw": {
          "leovegas": 5,
          "unibet": 5.1,
          "nordicbet": 4.85,
          "pmu": 4.75,
          "betsson": 4.85,
          "codere": 4.7,
          "onexbet": 5.06,
          "pinnacle": 4.99,
          "marathonbet": 4.9,
          "williamhill": 4.5,
          "betclic": 4.9,
          "winamax": 4.9,
          "tipico": 4.9,
          "betfair": 5.3,
          "betonlineag": 4.8,
          "coolbet": 4.75,
          "betanysports": 4.75,
          "matchbook": 5.3
        },
        "away": {
          "leovegas": 7.5,
          "unibet": 7.5,
          "nordicbet": 6.5,
          "pmu": 7,
          "betsson": 6.5,
          "codere": 6.4,
          "onexbet": 8.15,
          "pinnacle": 7.74,
          "marathonbet": 7.9,
          "williamhill": 7,
          "betclic": 6.75,
          "winamax": 6,
          "tipico": 7,
          "betfair": 8.2,
          "betonlineag": 7.6,
          "coolbet": 7.5,
          "betanysports": 7.25,
          "matchbook": 8.2
        }
      },
      "model": {
        "home": 0.6800881118841909,
        "draw": 0.19041825702221835,
        "away": 0.12949363109359066,
        "fromMarket": true
      }
    },
    {
      "id": "abaed47675a2fceaeb7174bec26cee4e",
      "group": "dom, 31 may",
      "time": "18:30",
      "home": "burgos",
      "away": "andorr",
      "odds": {
        "home": {
          "pmu": 1.4,
          "unibet": 1.49,
          "nordicbet": 1.52,
          "leovegas": 1.45,
          "betsson": 1.52,
          "codere": 1.51,
          "pinnacle": 1.56,
          "marathonbet": 1.51,
          "williamhill": 1.5,
          "betclic": 1.52,
          "winamax": 1.5,
          "tipico": 1.5,
          "betfair": 1.59,
          "betonlineag": 1.52,
          "coolbet": 1.53,
          "matchbook": 1.59,
          "betanysports": 1.54
        },
        "draw": {
          "pmu": 3.9,
          "unibet": 4.2,
          "nordicbet": 3.95,
          "leovegas": 4.1,
          "betsson": 3.95,
          "codere": 3.85,
          "pinnacle": 4.03,
          "marathonbet": 4.05,
          "williamhill": 3.8,
          "betclic": 4.05,
          "winamax": 4,
          "tipico": 3.9,
          "betfair": 4.2,
          "betonlineag": 3.9,
          "coolbet": 4.2,
          "matchbook": 4.2,
          "betanysports": 3.9
        },
        "away": {
          "pmu": 6,
          "unibet": 6.5,
          "nordicbet": 5.7,
          "leovegas": 6.25,
          "betsson": 5.7,
          "codere": 5.6,
          "pinnacle": 6.48,
          "marathonbet": 6.15,
          "williamhill": 6,
          "betclic": 5.75,
          "winamax": 5.6,
          "tipico": 6,
          "betfair": 6.8,
          "betonlineag": 6.4,
          "coolbet": 6.5,
          "matchbook": 6.8,
          "betanysports": 6.2
        }
      },
      "model": {
        "home": 0.6153609902164979,
        "draw": 0.23244457592696757,
        "away": 0.1521944338565345,
        "fromMarket": true
      }
    },
    {
      "id": "1515f82cb56fe27b7d52364adf5e0c10",
      "group": "dom, 31 may",
      "time": "18:30",
      "home": "cdcast",
      "away": "sdeiba",
      "odds": {
        "home": {
          "leovegas": 1.53,
          "betsson": 1.55,
          "nordicbet": 1.55,
          "unibet": 1.57,
          "pmu": 1.48,
          "codere": 1.53,
          "onexbet": 1.54,
          "pinnacle": 1.56,
          "marathonbet": 1.5,
          "williamhill": 1.53,
          "betclic": 1.53,
          "winamax": 1.54,
          "tipico": 1.5,
          "betfair": 1.59,
          "betonlineag": 1.55,
          "coolbet": 1.58,
          "matchbook": 1.59,
          "betanysports": 1.51
        },
        "draw": {
          "leovegas": 4.1,
          "betsson": 4.35,
          "nordicbet": 4.35,
          "unibet": 4.2,
          "pmu": 3.9,
          "codere": 4.2,
          "onexbet": 4.68,
          "pinnacle": 4.7,
          "marathonbet": 4.55,
          "williamhill": 4.2,
          "betclic": 4.35,
          "winamax": 4.5,
          "tipico": 4.4,
          "betfair": 4.9,
          "betonlineag": 4.5,
          "coolbet": 4.4,
          "matchbook": 4.9,
          "betanysports": 4.45
        },
        "away": {
          "leovegas": 5.1,
          "betsson": 4.95,
          "nordicbet": 4.95,
          "unibet": 5.25,
          "pmu": 4.9,
          "codere": 4.8,
          "onexbet": 5.55,
          "pinnacle": 5.31,
          "marathonbet": 5.4,
          "williamhill": 4.5,
          "betclic": 5,
          "winamax": 4.5,
          "tipico": 5.2,
          "betfair": 5.6,
          "betonlineag": 5,
          "coolbet": 5.25,
          "matchbook": 5.7,
          "betanysports": 5.1
        }
      },
      "model": {
        "home": 0.605470547147511,
        "draw": 0.21146657002069372,
        "away": 0.1830628828317953,
        "fromMarket": true
      }
    },
    {
      "id": "2a1a9a3351858aaf7915f0e8660c5110",
      "group": "dom, 31 may",
      "time": "18:30",
      "home": "realra",
      "away": "cadizc",
      "odds": {
        "home": {
          "unibet": 1.38,
          "pmu": 1.29,
          "leovegas": 1.34,
          "betsson": 1.33,
          "nordicbet": 1.33,
          "onexbet": 1.36,
          "pinnacle": 1.38,
          "marathonbet": 1.33,
          "williamhill": 1.35,
          "betclic": 1.35,
          "winamax": 1.32,
          "tipico": 1.32,
          "betfair": 1.39,
          "betonlineag": 1.37,
          "coolbet": 1.35,
          "matchbook": 1.39,
          "betanysports": 1.33
        },
        "draw": {
          "unibet": 4.9,
          "pmu": 4.5,
          "leovegas": 4.7,
          "betsson": 4.95,
          "nordicbet": 4.95,
          "onexbet": 5.24,
          "pinnacle": 5.14,
          "marathonbet": 5,
          "williamhill": 4.6,
          "betclic": 4.55,
          "winamax": 4.4,
          "tipico": 4.9,
          "betfair": 5.2,
          "betonlineag": 4.9,
          "coolbet": 5.25,
          "matchbook": 5.2,
          "betanysports": 4.9
        },
        "away": {
          "unibet": 7.6,
          "pmu": 7,
          "leovegas": 7.5,
          "betsson": 7.9,
          "nordicbet": 7.9,
          "onexbet": 8.5,
          "pinnacle": 8.09,
          "marathonbet": 8.3,
          "williamhill": 7.5,
          "betclic": 8.25,
          "winamax": 9,
          "tipico": 7.8,
          "betfair": 10,
          "betonlineag": 7,
          "coolbet": 8.25,
          "matchbook": 10,
          "betanysports": 7.5
        }
      },
      "model": {
        "home": 0.6928601997116511,
        "draw": 0.1910782041197929,
        "away": 0.1160615961685559,
        "fromMarket": true
      }
    },
    {
      "id": "291b968f6c03689fc9d571b0db8f68c6",
      "group": "dom, 31 may",
      "time": "18:30",
      "home": "deport",
      "away": "laspal",
      "odds": {
        "home": {
          "unibet": 3.25,
          "pmu": 3,
          "leovegas": 3.15,
          "betsson": 3.15,
          "nordicbet": 3.15,
          "codere": 3.1,
          "onexbet": 3.33,
          "pinnacle": 3.36,
          "marathonbet": 3.24,
          "williamhill": 3.1,
          "betclic": 3.2,
          "winamax": 3.2,
          "tipico": 3.2,
          "betfair": 3.45,
          "betonlineag": 3.35,
          "coolbet": 3.3,
          "matchbook": 3.45,
          "betanysports": 3.2
        },
        "draw": {
          "unibet": 3.4,
          "pmu": 3.15,
          "leovegas": 3.3,
          "betsson": 3.3,
          "nordicbet": 3.3,
          "codere": 3.25,
          "onexbet": 3.44,
          "pinnacle": 3.37,
          "marathonbet": 3.35,
          "williamhill": 3.2,
          "betclic": 3.37,
          "winamax": 3.4,
          "tipico": 3.3,
          "betfair": 3.55,
          "betonlineag": 3.2,
          "coolbet": 3.4,
          "matchbook": 3.55,
          "betanysports": 3.25
        },
        "away": {
          "unibet": 2.18,
          "pmu": 2.04,
          "leovegas": 2.12,
          "betsson": 2.15,
          "nordicbet": 2.15,
          "codere": 2.13,
          "onexbet": 2.21,
          "pinnacle": 2.25,
          "marathonbet": 2.15,
          "williamhill": 2.15,
          "betclic": 1.91,
          "winamax": 2,
          "tipico": 2.15,
          "betfair": 2.28,
          "betonlineag": 2.2,
          "coolbet": 2.2,
          "matchbook": 2.28,
          "betanysports": 2.16
        }
      },
      "model": {
        "home": 0.2880335030200215,
        "draw": 0.27883932665341393,
        "away": 0.43312717032656445,
        "fromMarket": true
      }
    },
    {
      "id": "aa584ba920cf41e5fbf08a8034181e33",
      "group": "dom, 31 may",
      "time": "18:30",
      "home": "zarago",
      "away": "malaga",
      "odds": {
        "home": {
          "pmu": 4.4,
          "unibet": 4.75,
          "nordicbet": 4.45,
          "leovegas": 4.6,
          "betsson": 4.45,
          "codere": 4.4,
          "onexbet": 5.04,
          "pinnacle": 4.89,
          "marathonbet": 4.9,
          "williamhill": 4.6,
          "betclic": 4.6,
          "winamax": 4.8,
          "tipico": 4.9,
          "betfair": 5.3,
          "betonlineag": 4.6,
          "coolbet": 4.75,
          "matchbook": 5.3,
          "betanysports": 4.95
        },
        "draw": {
          "pmu": 3.1,
          "unibet": 3.45,
          "nordicbet": 3.6,
          "leovegas": 3.25,
          "betsson": 3.6,
          "codere": 3.45,
          "onexbet": 3.73,
          "pinnacle": 3.71,
          "marathonbet": 3.62,
          "williamhill": 3.4,
          "betclic": 3.58,
          "winamax": 3.3,
          "tipico": 3.5,
          "betfair": 3.8,
          "betonlineag": 3.65,
          "coolbet": 3.75,
          "matchbook": 3.8,
          "betanysports": 3.55
        },
        "away": {
          "pmu": 1.7,
          "unibet": 1.81,
          "nordicbet": 1.72,
          "leovegas": 1.76,
          "betsson": 1.72,
          "codere": 1.72,
          "onexbet": 1.74,
          "pinnacle": 1.76,
          "marathonbet": 1.69,
          "williamhill": 1.7,
          "betclic": 1.72,
          "winamax": 1.7,
          "tipico": 1.67,
          "betfair": 1.81,
          "betonlineag": 1.76,
          "coolbet": 1.75,
          "matchbook": 1.81,
          "betanysports": 1.67
        }
      },
      "model": {
        "home": 0.19684032825999492,
        "draw": 0.264135319328254,
        "away": 0.539024352411751,
        "fromMarket": true
      }
    },
    {
      "id": "6e7dbb756b26aca56c81577545755e71",
      "group": "dom, 31 may",
      "time": "21:00",
      "home": "legane",
      "away": "cdmira",
      "odds": {
        "home": {
          "pmu": 1.91,
          "unibet": 2.05,
          "nordicbet": 2.15,
          "leovegas": 2,
          "betsson": 2.15,
          "codere": 2.12,
          "onexbet": 2.16,
          "pinnacle": 2.26,
          "marathonbet": 2.1,
          "williamhill": 2.15,
          "betclic": 2.12,
          "winamax": 2.1,
          "tipico": 2.1,
          "betfair": 2.26,
          "betonlineag": 2.2,
          "coolbet": 2.12,
          "betanysports": 2.16,
          "matchbook": 2.24
        },
        "draw": {
          "pmu": 3.25,
          "unibet": 3.45,
          "nordicbet": 3.35,
          "leovegas": 3.4,
          "betsson": 3.35,
          "codere": 3.3,
          "onexbet": 3.56,
          "pinnacle": 3.53,
          "marathonbet": 3.46,
          "williamhill": 3.25,
          "betclic": 3.43,
          "winamax": 3.45,
          "tipico": 3.4,
          "betfair": 3.6,
          "betonlineag": 3.4,
          "coolbet": 3.6,
          "betanysports": 3.35,
          "matchbook": 3.6
        },
        "away": {
          "pmu": 3.3,
          "unibet": 3.5,
          "nordicbet": 3.1,
          "leovegas": 3.4,
          "betsson": 3.1,
          "codere": 3.05,
          "onexbet": 3.35,
          "pinnacle": 3.2,
          "marathonbet": 3.25,
          "williamhill": 3.1,
          "betclic": 3.17,
          "winamax": 3,
          "tipico": 3.2,
          "betfair": 3.35,
          "betonlineag": 3.15,
          "coolbet": 3.3,
          "betanysports": 3.1,
          "matchbook": 3.35
        }
      },
      "model": {
        "home": 0.4381203178037209,
        "draw": 0.2720226559335051,
        "away": 0.2898570262627741,
        "fromMarket": true
      }
    },
    {
      "id": "ad5705b0b0ac75e1d73d7c5158050b7f",
      "group": "dom, 31 may",
      "time": "21:00",
      "home": "cordob",
      "away": "sdhues",
      "odds": {
        "home": {
          "leovegas": 1.56,
          "pmu": 1.5,
          "unibet": 1.61,
          "nordicbet": 1.62,
          "betsson": 1.62,
          "codere": 1.62,
          "onexbet": 1.66,
          "pinnacle": 1.67,
          "marathonbet": 1.61,
          "williamhill": 1.62,
          "betclic": 1.62,
          "winamax": 1.6,
          "tipico": 1.62,
          "betfair": 1.73,
          "betonlineag": 1.67,
          "coolbet": 1.73,
          "betanysports": 1.62,
          "matchbook": 1.72
        },
        "draw": {
          "leovegas": 3.55,
          "pmu": 3.4,
          "unibet": 3.65,
          "nordicbet": 3.6,
          "betsson": 3.6,
          "codere": 3.5,
          "onexbet": 3.95,
          "pinnacle": 3.87,
          "marathonbet": 3.84,
          "williamhill": 3.8,
          "betclic": 3.65,
          "winamax": 3.6,
          "tipico": 3.7,
          "betfair": 3.85,
          "betonlineag": 3.75,
          "coolbet": 3.85,
          "betanysports": 3.7,
          "matchbook": 3.9
        },
        "away": {
          "leovegas": 5.75,
          "pmu": 5.5,
          "unibet": 6,
          "nordicbet": 5.15,
          "betsson": 5.15,
          "codere": 5,
          "onexbet": 5.35,
          "pinnacle": 5.38,
          "marathonbet": 5.2,
          "williamhill": 4.6,
          "betclic": 5.25,
          "winamax": 5.1,
          "tipico": 5,
          "betfair": 5.9,
          "betonlineag": 5.1,
          "coolbet": 4.75,
          "betanysports": 5.1,
          "matchbook": 5.9
        }
      },
      "model": {
        "home": 0.5712082924102185,
        "draw": 0.2516599685483512,
        "away": 0.17713173904143015,
        "fromMarket": true
      }
    },
    {
      "id": "7fe097599618d3b2b8acb89d4afb87c8",
      "group": "dom, 31 may",
      "time": "16:00",
      "home": "saober",
      "away": "gremio",
      "odds": {
        "home": {
          "unibet": 2.85,
          "leovegas": 2.75,
          "nordicbet": 2.62,
          "betsson": 2.62,
          "betonlineag": 2.78,
          "coolbet": 2.7,
          "onexbet": 2.66,
          "marathonbet": 2.66,
          "pinnacle": 2.71,
          "sport888": 2.62,
          "williamhill": 2.62,
          "betfair": 2.8,
          "tipico": 2.45,
          "codere": 2.6,
          "matchbook": 2.8
        },
        "draw": {
          "unibet": 2.95,
          "leovegas": 2.85,
          "nordicbet": 2.88,
          "betsson": 2.88,
          "betonlineag": 2.82,
          "coolbet": 3,
          "onexbet": 2.85,
          "marathonbet": 2.85,
          "pinnacle": 2.94,
          "sport888": 2.8,
          "williamhill": 2.8,
          "betfair": 3,
          "tipico": 2.85,
          "codere": 2.85,
          "matchbook": 3
        },
        "away": {
          "unibet": 2.7,
          "leovegas": 2.63,
          "nordicbet": 2.82,
          "betsson": 2.82,
          "betonlineag": 2.88,
          "coolbet": 2.75,
          "onexbet": 2.85,
          "marathonbet": 2.85,
          "pinnacle": 3.04,
          "sport888": 2.8,
          "williamhill": 2.8,
          "betfair": 3.05,
          "tipico": 2.85,
          "codere": 2.8,
          "matchbook": 3.05
        }
      },
      "model": {
        "home": 0.3483096287089715,
        "draw": 0.3232767781606006,
        "away": 0.3284135931304279,
        "fromMarket": true
      }
    },
    {
      "id": "1994fde9631f467fc094fd25e7865ad1",
      "group": "dom, 31 may",
      "time": "16:00",
      "home": "londri",
      "away": "vilano",
      "odds": {
        "home": {
          "unibet": 2.4,
          "leovegas": 2.35,
          "nordicbet": 2.52,
          "betsson": 2.52,
          "betonlineag": 2.52,
          "coolbet": 2.45,
          "pinnacle": 2.64,
          "onexbet": 2.53,
          "marathonbet": 2.53,
          "betfair": 2.68,
          "sport888": 2.5,
          "williamhill": 2.5,
          "tipico": 2.6,
          "matchbook": 2.68
        },
        "draw": {
          "unibet": 3.2,
          "leovegas": 3.1,
          "nordicbet": 3,
          "betsson": 3,
          "betonlineag": 2.98,
          "coolbet": 3.2,
          "pinnacle": 3.08,
          "onexbet": 2.97,
          "marathonbet": 2.97,
          "betfair": 3.1,
          "sport888": 2.88,
          "williamhill": 2.88,
          "tipico": 2.95,
          "matchbook": 3.15
        },
        "away": {
          "unibet": 3,
          "leovegas": 2.9,
          "nordicbet": 2.82,
          "betsson": 2.82,
          "betonlineag": 3,
          "coolbet": 2.85,
          "pinnacle": 2.98,
          "onexbet": 2.88,
          "marathonbet": 2.88,
          "betfair": 3.1,
          "sport888": 2.9,
          "williamhill": 2.9,
          "tipico": 2.6,
          "matchbook": 3.1
        }
      },
      "model": {
        "home": 0.3698102487416561,
        "draw": 0.3084316514312493,
        "away": 0.3217580998270947,
        "fromMarket": true
      }
    },
    {
      "id": "abd86e36aca36e41e1b0b15cf990a4a0",
      "group": "dom, 31 may",
      "time": "21:00",
      "home": "ceara",
      "away": "operar",
      "odds": {
        "home": {
          "leovegas": 1.94,
          "unibet": 2,
          "nordicbet": 1.95,
          "pinnacle": 2.01,
          "betsson": 1.95,
          "betonlineag": 1.97,
          "coolbet": 2,
          "marathonbet": 1.96,
          "onexbet": 1.98,
          "betfair": 2.04,
          "sport888": 2,
          "williamhill": 2,
          "tipico": 1.83,
          "codere": 1.94,
          "matchbook": 2.06
        },
        "draw": {
          "leovegas": 3.15,
          "unibet": 3.25,
          "nordicbet": 3.15,
          "pinnacle": 3.29,
          "betsson": 3.15,
          "betonlineag": 3.15,
          "coolbet": 3.2,
          "marathonbet": 3.18,
          "onexbet": 3.18,
          "betfair": 3.3,
          "sport888": 3.1,
          "williamhill": 3.1,
          "tipico": 3.1,
          "codere": 3.15,
          "matchbook": 3.3
        },
        "away": {
          "leovegas": 3.85,
          "unibet": 3.95,
          "nordicbet": 3.95,
          "pinnacle": 4.19,
          "betsson": 3.95,
          "betonlineag": 4.1,
          "coolbet": 3.85,
          "marathonbet": 3.92,
          "onexbet": 3.93,
          "betfair": 4.4,
          "sport888": 3.8,
          "williamhill": 3.8,
          "tipico": 4.2,
          "codere": 3.95,
          "matchbook": 4.4
        }
      },
      "model": {
        "home": 0.4732704030823127,
        "draw": 0.2936007459865255,
        "away": 0.2331288509311616,
        "fromMarket": true
      }
    },
    {
      "id": "8d82fd202f46ac383453784935982106",
      "group": "lun, 01 jun",
      "time": "01:30",
      "home": "cuiaba",
      "away": "clubed",
      "odds": {
        "home": {
          "unibet": 2.45,
          "leovegas": 2.38,
          "betsson": 2.45,
          "nordicbet": 2.45,
          "pinnacle": 2.56,
          "betonlineag": 2.52,
          "marathonbet": 2.49,
          "coolbet": 2.5,
          "onexbet": 2.51,
          "betfair": 2.62,
          "sport888": 2.5,
          "williamhill": 2.5,
          "codere": 2.41,
          "matchbook": 2.64
        },
        "draw": {
          "unibet": 3,
          "leovegas": 2.95,
          "betsson": 2.92,
          "nordicbet": 2.92,
          "pinnacle": 2.91,
          "betonlineag": 2.86,
          "marathonbet": 2.84,
          "coolbet": 3,
          "onexbet": 2.84,
          "betfair": 2.9,
          "sport888": 2.75,
          "williamhill": 2.75,
          "codere": 2.85,
          "matchbook": 2.94
        },
        "away": {
          "unibet": 3.1,
          "leovegas": 3,
          "betsson": 3,
          "nordicbet": 3,
          "pinnacle": 3.23,
          "betonlineag": 3.15,
          "marathonbet": 3.08,
          "coolbet": 2.95,
          "onexbet": 3.1,
          "betfair": 3.3,
          "sport888": 3.1,
          "williamhill": 3.1,
          "codere": 2.9,
          "matchbook": 3.3
        }
      },
      "model": {
        "home": 0.37406783807955085,
        "draw": 0.32361557798198026,
        "away": 0.30231658393846883,
        "fromMarket": true
      }
    },
    {
      "id": "3d7f63e022bde2dd7ac9c739a6be19bf",
      "group": "mar, 02 jun",
      "time": "00:00",
      "home": "pontep",
      "away": "bot",
      "odds": {
        "home": {
          "nordicbet": 2.72,
          "betsson": 2.72,
          "onexbet": 2.76,
          "sport888": 2.75,
          "williamhill": 2.75,
          "marathonbet": 2.76,
          "coolbet": 2.65,
          "leovegas": 2.6,
          "unibet": 2.65,
          "betonlineag": 2.82,
          "pinnacle": 2.84,
          "codere": 2.65,
          "matchbook": 2.86,
          "betfair": 2.84
        },
        "draw": {
          "nordicbet": 2.92,
          "betsson": 2.92,
          "onexbet": 2.84,
          "sport888": 2.8,
          "williamhill": 2.8,
          "marathonbet": 2.84,
          "coolbet": 3,
          "leovegas": 3.05,
          "unibet": 3.15,
          "betonlineag": 2.76,
          "pinnacle": 2.88,
          "codere": 2.85,
          "matchbook": 3.05,
          "betfair": 3.05
        },
        "away": {
          "nordicbet": 2.72,
          "betsson": 2.72,
          "onexbet": 2.74,
          "sport888": 2.75,
          "williamhill": 2.75,
          "marathonbet": 2.74,
          "coolbet": 2.75,
          "leovegas": 2.65,
          "unibet": 2.75,
          "betonlineag": 2.78,
          "pinnacle": 2.81,
          "codere": 2.65,
          "matchbook": 2.88,
          "betfair": 2.8
        }
      },
      "model": {
        "home": 0.3407101316769017,
        "draw": 0.3197758824261492,
        "away": 0.33951398589694903,
        "fromMarket": true
      }
    },
    {
      "id": "ea30e9681a6618720cae67524b78b985",
      "group": "dom, 31 may",
      "time": "18:30",
      "home": "gent",
      "away": "genk",
      "odds": {
        "home": {
          "pinnacle": 2.69,
          "betsson": 2.6,
          "betonlineag": 2.58,
          "nordicbet": 2.6,
          "coolbet": 2.65,
          "betfair": 2.74,
          "onexbet": 2.66,
          "suprabets": 2.59,
          "marathonbet": 2.58,
          "sport888": 2.6,
          "williamhill": 2.6,
          "pmu": 2.6,
          "unibet": 2.7,
          "leovegas": 2.6,
          "betclic": 2.65,
          "everygame": 2.6,
          "matchbook": 2.74
        },
        "draw": {
          "pinnacle": 3.63,
          "betsson": 3.5,
          "betonlineag": 3.4,
          "nordicbet": 3.5,
          "coolbet": 3.6,
          "betfair": 3.7,
          "onexbet": 3.58,
          "suprabets": 3.52,
          "marathonbet": 3.5,
          "sport888": 3.3,
          "williamhill": 3.3,
          "pmu": 3.35,
          "unibet": 3.55,
          "leovegas": 3.35,
          "betclic": 3.63,
          "everygame": 3.5,
          "matchbook": 3.7
        },
        "away": {
          "pinnacle": 2.59,
          "betsson": 2.55,
          "betonlineag": 2.62,
          "nordicbet": 2.55,
          "coolbet": 2.4,
          "betfair": 2.66,
          "onexbet": 2.55,
          "suprabets": 2.5,
          "marathonbet": 2.51,
          "sport888": 2.45,
          "williamhill": 2.45,
          "pmu": 2.28,
          "unibet": 2.38,
          "leovegas": 2.3,
          "betclic": 2.45,
          "everygame": 2.5,
          "matchbook": 2.66
        }
      },
      "model": {
        "home": 0.3559155445095501,
        "draw": 0.2676100884726435,
        "away": 0.3764743670178064,
        "fromMarket": true
      }
    },
    {
      "id": "ed7bfd345ed5aaf4672a8776adeb370b",
      "group": "dom, 31 may",
      "time": "14:00",
      "home": "bkhack",
      "away": "hammar",
      "odds": {
        "home": {
          "pmu": 2.6,
          "unibet": 2.95,
          "leovegas": 2.85,
          "betclic": 2.78,
          "onexbet": 2.82,
          "winamax": 2.65,
          "gtbets": 2.86,
          "betonlineag": 2.8,
          "nordicbet": 2.88,
          "betsson": 2.88,
          "betfair": 3,
          "sport888": 2.7,
          "williamhill": 2.7,
          "pinnacle": 2.91,
          "coolbet": 2.85,
          "tipico": 2.75,
          "everygame": 2.8,
          "matchbook": 3,
          "betanysports": 2.85
        },
        "draw": {
          "pmu": 3.25,
          "unibet": 3.75,
          "leovegas": 3.55,
          "betclic": 3.63,
          "onexbet": 3.62,
          "winamax": 3.65,
          "gtbets": 3.61,
          "betonlineag": 3.7,
          "nordicbet": 3.65,
          "betsson": 3.65,
          "betfair": 3.85,
          "sport888": 3.4,
          "williamhill": 3.4,
          "pinnacle": 3.84,
          "coolbet": 3.7,
          "tipico": 3.6,
          "everygame": 3.75,
          "matchbook": 3.85,
          "betanysports": 3.75
        },
        "away": {
          "pmu": 2.1,
          "unibet": 2.35,
          "leovegas": 2.28,
          "betclic": 2.25,
          "onexbet": 2.29,
          "winamax": 2.2,
          "gtbets": 2.22,
          "betonlineag": 2.34,
          "nordicbet": 2.25,
          "betsson": 2.25,
          "betfair": 2.4,
          "sport888": 2.3,
          "williamhill": 2.3,
          "pinnacle": 2.28,
          "coolbet": 2.39,
          "tipico": 2.25,
          "everygame": 2.25,
          "matchbook": 2.4,
          "betanysports": 2.24
        }
      },
      "model": {
        "home": 0.33198013169474366,
        "draw": 0.25739427494154016,
        "away": 0.4106255933637162,
        "fromMarket": true
      }
    },
    {
      "id": "a0a07ce79ff1a6ff4d9219a4556dc462",
      "group": "dom, 31 may",
      "time": "14:00",
      "home": "degerf",
      "away": "ifbrom",
      "odds": {
        "home": {
          "pmu": 2.16,
          "unibet": 2.43,
          "leovegas": 2.33,
          "onexbet": 2.36,
          "winamax": 2.35,
          "betsson": 2.38,
          "nordicbet": 2.38,
          "betonlineag": 2.38,
          "betclic": 2.32,
          "pinnacle": 2.39,
          "betfair": 2.42,
          "sport888": 2.3,
          "williamhill": 2.3,
          "tipico": 2.3,
          "gtbets": 2.38,
          "coolbet": 2.26,
          "everygame": 2.3,
          "matchbook": 2.44,
          "betanysports": 2.35
        },
        "draw": {
          "pmu": 3,
          "unibet": 3.45,
          "leovegas": 3.25,
          "onexbet": 3.18,
          "winamax": 3.4,
          "betsson": 3.2,
          "nordicbet": 3.2,
          "betonlineag": 3.2,
          "betclic": 3.2,
          "pinnacle": 3.29,
          "betfair": 3.4,
          "sport888": 3,
          "williamhill": 3,
          "tipico": 3.2,
          "gtbets": 3.23,
          "coolbet": 3.4,
          "everygame": 3.25,
          "matchbook": 3.4,
          "betanysports": 3.2
        },
        "away": {
          "pmu": 2.7,
          "unibet": 3.1,
          "leovegas": 2.95,
          "onexbet": 3.03,
          "winamax": 2.6,
          "betsson": 3,
          "nordicbet": 3,
          "betonlineag": 3.1,
          "betclic": 2.98,
          "pinnacle": 3.12,
          "betfair": 3.3,
          "sport888": 3,
          "williamhill": 3,
          "tipico": 2.95,
          "gtbets": 3.02,
          "coolbet": 3.3,
          "everygame": 3.05,
          "matchbook": 3.3,
          "betanysports": 3.05
        }
      },
      "model": {
        "home": 0.39983498220575164,
        "draw": 0.29000950138970794,
        "away": 0.3101555164045404,
        "fromMarket": true
      }
    },
    {
      "id": "51bda79539f0ec0b00071bcba9c50c7f",
      "group": "dom, 31 may",
      "time": "14:00",
      "home": "vaster",
      "away": "ifkgot",
      "odds": {
        "home": {
          "pmu": 2.33,
          "leovegas": 2.55,
          "unibet": 2.65,
          "onexbet": 2.62,
          "winamax": 2.5,
          "betclic": 2.6,
          "betonlineag": 2.68,
          "betsson": 2.62,
          "nordicbet": 2.68,
          "betfair": 2.8,
          "pinnacle": 2.71,
          "coolbet": 2.64,
          "tipico": 2.6,
          "everygame": 2.6,
          "matchbook": 2.8,
          "sport888": 2.6,
          "williamhill": 2.6,
          "betanysports": 2.66
        },
        "draw": {
          "pmu": 3.1,
          "leovegas": 3.4,
          "unibet": 3.6,
          "onexbet": 3.32,
          "winamax": 3.35,
          "betclic": 3.33,
          "betonlineag": 3.3,
          "betsson": 3.3,
          "nordicbet": 3.2,
          "betfair": 3.55,
          "pinnacle": 3.42,
          "coolbet": 3.5,
          "tipico": 3.2,
          "everygame": 3.3,
          "matchbook": 3.55,
          "sport888": 3.4,
          "williamhill": 3.4,
          "betanysports": 3.3
        },
        "away": {
          "pmu": 2.4,
          "leovegas": 2.6,
          "unibet": 2.75,
          "onexbet": 2.57,
          "winamax": 2.5,
          "betclic": 2.53,
          "betonlineag": 2.66,
          "betsson": 2.58,
          "nordicbet": 2.62,
          "betfair": 2.74,
          "pinnacle": 2.63,
          "coolbet": 2.67,
          "tipico": 2.55,
          "everygame": 2.6,
          "matchbook": 2.74,
          "sport888": 2.6,
          "williamhill": 2.6,
          "betanysports": 2.58
        }
      },
      "model": {
        "home": 0.35883752967710786,
        "draw": 0.2800598410439553,
        "away": 0.3611026292789368,
        "fromMarket": true
      }
    },
    {
      "id": "c3afa656160fb3ea8d768cb4c68bac23",
      "group": "dom, 31 may",
      "time": "18:30",
      "home": "deport",
      "away": "coquim",
      "odds": {
        "home": {
          "winamax": 2.5,
          "nordicbet": 2.68,
          "onexbet": 2.66,
          "marathonbet": 2.66,
          "coolbet": 2.6,
          "leovegas": 2.63,
          "unibet": 2.63,
          "pinnacle": 2.76,
          "sport888": 2.62,
          "tipico": 2.65,
          "gtbets": 2.59,
          "betsson": 2.68,
          "everygame": 2.55,
          "betonlineag": 2.7,
          "codere": 2.6,
          "betfair": 2.74,
          "matchbook": 2.8
        },
        "draw": {
          "winamax": 3.3,
          "nordicbet": 3.35,
          "onexbet": 3.34,
          "marathonbet": 3.34,
          "coolbet": 3.45,
          "leovegas": 3.3,
          "unibet": 3.3,
          "pinnacle": 3.49,
          "sport888": 3.1,
          "tipico": 2.95,
          "gtbets": 3.37,
          "betsson": 3.35,
          "everygame": 3.2,
          "betonlineag": 3.3,
          "codere": 3.3,
          "betfair": 3.6,
          "matchbook": 3.7
        },
        "away": {
          "winamax": 2.4,
          "nordicbet": 2.52,
          "onexbet": 2.48,
          "marathonbet": 2.48,
          "coolbet": 2.65,
          "leovegas": 2.48,
          "unibet": 2.48,
          "pinnacle": 2.57,
          "sport888": 2.45,
          "tipico": 2.55,
          "gtbets": 2.65,
          "betsson": 2.52,
          "everygame": 2.4,
          "betonlineag": 2.56,
          "codere": 2.5,
          "betfair": 2.62,
          "matchbook": 2.62
        }
      },
      "model": {
        "home": 0.3515043536736923,
        "draw": 0.2795753545632657,
        "away": 0.36892029176304186,
        "fromMarket": true
      }
    },
    {
      "id": "c9c3e8bdec4d576651d513313ee174ee",
      "group": "dom, 31 may",
      "time": "21:00",
      "home": "huachi",
      "away": "univer",
      "odds": {
        "home": {
          "winamax": 2.9,
          "nordicbet": 3.15,
          "onexbet": 3.17,
          "marathonbet": 3.15,
          "coolbet": 3.2,
          "unibet": 3.15,
          "leovegas": 3.15,
          "pinnacle": 3.27,
          "sport888": 3,
          "tipico": 3.2,
          "gtbets": 3.06,
          "betsson": 3.15,
          "everygame": 3.1,
          "betonlineag": 3.05,
          "codere": 3.05,
          "betfair": 3.25,
          "matchbook": 3.3
        },
        "draw": {
          "winamax": 3.25,
          "nordicbet": 3.35,
          "onexbet": 3.3,
          "marathonbet": 3.3,
          "coolbet": 3.4,
          "unibet": 3.3,
          "leovegas": 3.3,
          "pinnacle": 3.47,
          "sport888": 3.1,
          "tipico": 3.3,
          "gtbets": 3.41,
          "betsson": 3.35,
          "everygame": 3.25,
          "betonlineag": 3.35,
          "codere": 3.25,
          "betfair": 3.45,
          "matchbook": 3.5
        },
        "away": {
          "winamax": 2.15,
          "nordicbet": 2.18,
          "onexbet": 2.2,
          "marathonbet": 2.18,
          "coolbet": 2.25,
          "unibet": 2.18,
          "leovegas": 2.18,
          "pinnacle": 2.25,
          "sport888": 2.15,
          "tipico": 2.05,
          "gtbets": 2.22,
          "betsson": 2.18,
          "everygame": 2.15,
          "betonlineag": 2.3,
          "codere": 2.21,
          "betfair": 2.32,
          "matchbook": 2.32
        }
      },
      "model": {
        "home": 0.29731983460324996,
        "draw": 0.27978431516467456,
        "away": 0.4228958502320756,
        "fromMarket": true
      }
    },
    {
      "id": "677db18f6beb5ea501de992675215458",
      "group": "dom, 31 may",
      "time": "23:30",
      "home": "ohiggi",
      "away": "everto",
      "odds": {
        "home": {
          "winamax": 1.86,
          "nordicbet": 1.92,
          "onexbet": 1.91,
          "marathonbet": 1.89,
          "coolbet": 1.92,
          "leovegas": 2,
          "unibet": 2,
          "pinnacle": 1.95,
          "sport888": 1.91,
          "tipico": 1.77,
          "gtbets": 1.94,
          "betsson": 1.92,
          "everygame": 1.85,
          "betonlineag": 1.96,
          "codere": 1.9,
          "betfair": 1.98,
          "matchbook": 1.99
        },
        "draw": {
          "winamax": 3.25,
          "nordicbet": 3.35,
          "onexbet": 3.36,
          "marathonbet": 3.36,
          "coolbet": 3.5,
          "leovegas": 3.2,
          "unibet": 3.2,
          "pinnacle": 3.48,
          "sport888": 3.1,
          "tipico": 3.4,
          "gtbets": 3.38,
          "betsson": 3.35,
          "everygame": 3.25,
          "betonlineag": 3.35,
          "codere": 3.2,
          "betfair": 3.5,
          "matchbook": 3.6
        },
        "away": {
          "winamax": 3.55,
          "nordicbet": 3.95,
          "onexbet": 3.96,
          "marathonbet": 3.95,
          "coolbet": 4.1,
          "leovegas": 3.7,
          "unibet": 3.7,
          "pinnacle": 4.07,
          "sport888": 3.7,
          "tipico": 4,
          "gtbets": 4.03,
          "betsson": 3.95,
          "everygame": 3.65,
          "betonlineag": 3.9,
          "codere": 3.7,
          "betfair": 4.2,
          "matchbook": 4.3
        }
      },
      "model": {
        "home": 0.4835587545184558,
        "draw": 0.27813251355681357,
        "away": 0.23830873192473054,
        "fromMarket": true
      }
    },
    {
      "id": "70299119d94a755f9d2d8cb56ec48a52",
      "group": "lun, 01 jun",
      "time": "02:00",
      "home": "palest",
      "away": "audaxi",
      "odds": {
        "home": {
          "marathonbet": 1.91,
          "onexbet": 1.93,
          "leovegas": 1.95,
          "unibet": 1.95,
          "tipico": 1.8,
          "coolbet": 1.95,
          "winamax": 1.88,
          "pinnacle": 1.95,
          "betfair": 1.98,
          "sport888": 1.91,
          "betsson": 1.92,
          "nordicbet": 1.92,
          "gtbets": 1.97,
          "betonlineag": 1.92,
          "everygame": 1.83,
          "codere": 1.9,
          "matchbook": 2
        },
        "draw": {
          "marathonbet": 3.6,
          "onexbet": 3.6,
          "leovegas": 3.4,
          "unibet": 3.4,
          "tipico": 3.5,
          "coolbet": 3.65,
          "winamax": 3.5,
          "pinnacle": 3.8,
          "betfair": 3.7,
          "sport888": 3.4,
          "betsson": 3.7,
          "nordicbet": 3.7,
          "gtbets": 3.55,
          "betonlineag": 3.7,
          "everygame": 3.45,
          "codere": 3.4,
          "matchbook": 3.75
        },
        "away": {
          "marathonbet": 3.6,
          "onexbet": 3.6,
          "leovegas": 3.65,
          "unibet": 3.65,
          "tipico": 3.8,
          "coolbet": 3.8,
          "winamax": 3.35,
          "pinnacle": 3.69,
          "betfair": 3.95,
          "sport888": 3.4,
          "betsson": 3.55,
          "nordicbet": 3.55,
          "gtbets": 3.7,
          "betonlineag": 3.7,
          "everygame": 3.35,
          "codere": 3.45,
          "matchbook": 4
        }
      },
      "model": {
        "home": 0.48369368355348313,
        "draw": 0.26009258849606426,
        "away": 0.25621372795045255,
        "fromMarket": true
      }
    },
    {
      "id": "a061244e38d1caddbca6103b8a0f88e7",
      "group": "dom, 31 may",
      "time": "13:00",
      "home": "tianji",
      "away": "dalian",
      "odds": {
        "home": {
          "nordicbet": 2.92,
          "betonlineag": 3,
          "marathonbet": 2.91,
          "betsson": 2.92,
          "coolbet": 2.9,
          "pinnacle": 3.07,
          "onexbet": 3.03,
          "winamax": 2.8,
          "sport888": 2.9,
          "williamhill": 2.9,
          "tipico": 2.95,
          "gtbets": 2.95,
          "leovegas": 2.8,
          "unibet": 2.85,
          "codere": 2.85,
          "betfair": 3.1,
          "matchbook": 3.15,
          "everygame": 2.9
        },
        "draw": {
          "nordicbet": 3.15,
          "betonlineag": 3.25,
          "marathonbet": 3.15,
          "betsson": 3.15,
          "coolbet": 3.25,
          "pinnacle": 3.3,
          "onexbet": 3.23,
          "winamax": 3.25,
          "sport888": 3,
          "williamhill": 3,
          "tipico": 3.1,
          "gtbets": 3.21,
          "leovegas": 3.05,
          "unibet": 3.1,
          "codere": 3.15,
          "betfair": 3.35,
          "matchbook": 3.35,
          "everygame": 3.1
        },
        "away": {
          "nordicbet": 2.38,
          "betonlineag": 2.42,
          "marathonbet": 2.39,
          "betsson": 2.38,
          "coolbet": 2.45,
          "pinnacle": 2.44,
          "onexbet": 2.45,
          "winamax": 2.3,
          "sport888": 2.38,
          "williamhill": 2.38,
          "tipico": 2.35,
          "gtbets": 2.45,
          "leovegas": 2.4,
          "unibet": 2.45,
          "codere": 2.35,
          "betfair": 2.54,
          "matchbook": 2.54,
          "everygame": 2.3
        }
      },
      "model": {
        "home": 0.3178859641753221,
        "draw": 0.2943121251041469,
        "away": 0.3878019107205311,
        "fromMarket": true
      }
    },
    {
      "id": "d599bc2c954d92dfcf68727b89147d00",
      "group": "dom, 31 may",
      "time": "13:35",
      "home": "wuhant",
      "away": "yunnan",
      "odds": {
        "home": {
          "nordicbet": 2.72,
          "betonlineag": 2.84,
          "marathonbet": 2.8,
          "betsson": 2.72,
          "coolbet": 2.75,
          "pinnacle": 2.88,
          "onexbet": 2.88,
          "winamax": 2.6,
          "sport888": 2.8,
          "williamhill": 2.8,
          "tipico": 2.75,
          "gtbets": 2.83,
          "unibet": 2.65,
          "leovegas": 2.6,
          "codere": 2.7,
          "betfair": 2.9,
          "matchbook": 2.9,
          "everygame": 2.75
        },
        "draw": {
          "nordicbet": 3.55,
          "betonlineag": 3.7,
          "marathonbet": 3.58,
          "betsson": 3.55,
          "coolbet": 3.85,
          "pinnacle": 3.8,
          "onexbet": 3.69,
          "winamax": 3.55,
          "sport888": 3.4,
          "williamhill": 3.4,
          "tipico": 3.6,
          "gtbets": 3.61,
          "unibet": 3.5,
          "leovegas": 3.4,
          "codere": 3.55,
          "betfair": 3.9,
          "matchbook": 3.95,
          "everygame": 3.5
        },
        "away": {
          "nordicbet": 2.3,
          "betonlineag": 2.32,
          "marathonbet": 2.26,
          "betsson": 2.3,
          "coolbet": 2.3,
          "pinnacle": 2.33,
          "onexbet": 2.33,
          "winamax": 2.2,
          "sport888": 2.25,
          "williamhill": 2.25,
          "tipico": 2.25,
          "gtbets": 2.29,
          "unibet": 2.45,
          "leovegas": 2.4,
          "codere": 2.29,
          "betfair": 2.4,
          "matchbook": 2.4,
          "everygame": 2.2
        }
      },
      "model": {
        "home": 0.33695524038824987,
        "draw": 0.2584297774979964,
        "away": 0.40461498211375374,
        "fromMarket": true
      }
    }
  ],
  "COMBOS": [
    {
      "id": "c1",
      "tier": "single",
      "conf": 35,
      "name": "Combinada del Día",
      "legs": [
        {
          "match": "Palmeiras – Chapecoense",
          "pick": "Palmeiras",
          "odd": 1.33,
          "book": "matchbook"
        },
        {
          "match": "Real Racing Club de Santander – Cádiz CF",
          "pick": "Real Racing Club de Santander",
          "odd": 1.39,
          "book": "betfair"
        },
        {
          "match": "Almería – Real Valladolid CF",
          "pick": "Almería",
          "odd": 1.42,
          "book": "betfair"
        }
      ]
    },
    {
      "id": "c2",
      "tier": "all",
      "conf": 35,
      "name": "Combinada Segura",
      "legs": [
        {
          "match": "Palmeiras – Chapecoense",
          "pick": "Palmeiras",
          "odd": 1.33,
          "book": "matchbook"
        },
        {
          "match": "Real Racing Club de Santander – Cádiz CF",
          "pick": "Real Racing Club de Santander",
          "odd": 1.39,
          "book": "betfair"
        },
        {
          "match": "Almería – Real Valladolid CF",
          "pick": "Almería",
          "odd": 1.42,
          "book": "betfair"
        }
      ]
    },
    {
      "id": "c3",
      "tier": "all",
      "conf": 21,
      "name": "Combinada Larga",
      "legs": [
        {
          "match": "Palmeiras – Chapecoense",
          "pick": "Palmeiras",
          "odd": 1.33,
          "book": "matchbook"
        },
        {
          "match": "Real Racing Club de Santander – Cádiz CF",
          "pick": "Real Racing Club de Santander",
          "odd": 1.39,
          "book": "betfair"
        },
        {
          "match": "Almería – Real Valladolid CF",
          "pick": "Almería",
          "odd": 1.42,
          "book": "betfair"
        },
        {
          "match": "Burgos CF – Andorra CF",
          "pick": "Burgos CF",
          "odd": 1.59,
          "book": "betfair"
        }
      ]
    }
  ],
  "RECORD": [
    {
      "id": "b32633aa2442ef8135cd962344d7b4b2",
      "date": "30 MAY",
      "pick": "Grêmio",
      "match": "Grêmio – Corinthians",
      "odd": 3.3,
      "book": "matchbook",
      "stake": 1,
      "result": "L"
    },
    {
      "id": "05d40cc47e24d558e805edcccf22f769",
      "date": "30 MAY",
      "pick": "VPS Vaasa",
      "match": "TPS Turku – VPS Vaasa",
      "odd": 2.51,
      "book": "coolbet",
      "stake": 1,
      "result": "L"
    }
  ],
  "PENDING": [
    {
      "id": "ed7bfd345ed5aaf4672a8776adeb370b",
      "sport": "soccer_sweden_allsvenskan",
      "ts": 1780228800000,
      "date": "31 MAY",
      "match": "BK Hacken – Hammarby IF",
      "pickKey": "home",
      "pickLabel": "BK Hacken",
      "odd": 3.1,
      "book": "coolbet"
    }
  ]
}